setup.py
weeblycloud/Account.py
weeblycloud/Blog.py
weeblycloud/BlogPost.py
weeblycloud/CloudResource.py
weeblycloud/Deleteable.py
weeblycloud/Form.py
weeblycloud/FormEntry.py
weeblycloud/Group.py
weeblycloud/Member.py
weeblycloud/Page.py
weeblycloud/PaginatedList.py
weeblycloud/Plan.py
weeblycloud/SaveableResource.py
weeblycloud/Site.py
weeblycloud/Theme.py
weeblycloud/User.py
weeblycloud/__init__.py
weeblycloud.egg-info/PKG-INFO
weeblycloud.egg-info/SOURCES.txt
weeblycloud.egg-info/dependency_links.txt
weeblycloud.egg-info/requires.txt
weeblycloud.egg-info/top_level.txt
weeblycloud.egg-info/zip-safe